[{"name":"Pavel","id":0,"age":38},{"name":"Petya","id":1,"age":29},{"name":"Artur","id":2,"age":25},{"name":"Artyom","id":3,"age":24},{"name":"Petya","id":4,"age":22},{"name":"Artur","id":5,"age":30},{"name":"Vasya","id":6,"age":23},{"name":"Artyom","id":7,"age":36},{"name":"Artyom","id":8,"age":30},{"name":"Petya","id":9,"age":31},{"name":"Artur","id":10,"age":40},{"name":"Petya","id":11,"age":43},{"name":"Artyom","id":12,"age":38},{"name":"Pavel","id":13,"age":38},{"name":"Pavel","id":14,"age":37},{"name":"Pavel","id":15,"age":40},{"name":"Vasya","id":16,"age":20},{"name":"Pavel","id":17,"age":34},{"name":"Pavel","id":18,"age":20},{"name":"Petya","id":19,"age":22},{"name":"Artur","id":20,"age":31},{"name":"Vasya","id":21,"age":39},{"name":"Artyom","id":22,"age":35},{"name":"Petya","id":23,"age":38},{"name":"Artyom","id":24,"age":26},{"name":"Artyom","id":25,"age":39},{"name":"Artyom","id":26,"age":27},{"name":"Pavel","id":27,"age":45},{"name":"Vasya","id":28,"age":19},{"name":"Pavel","id":29,"age":36},{"name":"Petya","id":30,"age":31},{"name":"Artur","id":31,"age":21},{"name":"Vasya","id":32,"age":38},{"name":"Pavel","id":33,"age":28},{"name":"Artyom","id":34,"age":30},{"name":"Artur","id":35,"age":22},{"name":"Vasya","id":36,"age":32},{"name":"Artyom","id":37,"age":25},{"name":"Petya","id":38,"age":23},{"name":"Artur","id":39,"age":26},{"name":"Petya","id":40,"age":23},{"name":"Pavel","id":41,"age":43},{"name":"Petya","id":42,"age":29},{"name":"Pavel","id":43,"age":20},{"name":"Petya","id":44,"age":26},{"name":"Artyom","id":45,"age":28},{"name":"Artyom","id":46,"age":24},{"name":"Pavel","id":47,"age":32},{"name":"Artyom","id":48,"age":33},{"name":"Pavel","id":49,"age":39}]